djpush/__init__.py
djpush/admin.py
djpush/apps.py
djpush/models.py
djpush/schedulers.py
djpush/test_models.py
djpush/test_schedulers.py
djpush/translation.py
djpush/views.py
djpush/migrations/0001_initial.py
djpush/migrations/__init__.py
djpush-0.9.91.dist-info/DESCRIPTION.rst
djpush-0.9.91.dist-info/METADATA
djpush-0.9.91.dist-info/RECORD
djpush-0.9.91.dist-info/WHEEL
djpush-0.9.91.dist-info/metadata.json
djpush-0.9.91.dist-info/top_level.txt
