Metadata-Version: 2.0
Name: djpush
Version: 0.9.91
Summary: Manage programatic *Push Notifications* from Django admin
Home-page: https://github.com/alej0varas/djpush
Author: Alexandre Varas
Author-email: alej0varas@gmail.com
License: GPL v3
Platform: UNKNOWN
Classifier: Topic :: Internet :: WWW/HTTP :: Dynamic Content
Classifier: Intended Audience :: Developers
Classifier: Programming Language :: Python
Classifier: Programming Language :: Python :: 3
Classifier: Programming Language :: Python :: 3.2
Classifier: Programming Language :: Python :: 3.3
Classifier: Programming Language :: Python :: 3.4
Classifier: Programming Language :: Python :: 3.5
Classifier: Framework :: Django
Classifier: Framework :: Django :: 1.10
Classifier: Framework :: Django :: 1.11
Classifier: Development Status :: 4 - Beta
Classifier: Operating System :: OS Independent
Requires-Dist: pypn
Requires-Dist: requests
Requires-Dist: django-timezone-field
